{
  "source": {
    "type": "youtube",
    "input": "https://youtu.be/FsqHMUQNiGg",
    "videoId": "FsqHMUQNiGg",
    "title": "【马来西亚东海岸自驾游-EP1】 跨越2000km游走全马最美沿海公路！从柔佛出发探索沿途各大海滩 关丹超美瀑布 Sungai Pandan Waterfall 海边巨石壁画  彭亨佛教会 品尝美食",
    "publishedAt": "2025-07-18T11:00:26Z",
    "channelTitle": "Jayden & Qing 一起看世界"
  },
  "country": "Malaysia",
  "category": "attraction",
  "extractedCount": 30,
  "normalizedCount": 30,
  "items": [
    {
      "name": "【东海岸自驾游 EP1】正式上线！ 这一次 我们决定玩点大的！",
      "name_cn": null,
      "category": "attraction",
      "region_name": null,
      "country": "Malaysia",
      "address": "【东海岸自驾游 EP1】正式上线！ 这一次 我们决定玩点大的！ Malaysia",
      "latitude": null,
      "longitude": null,
      "description": "From YouTube: 【马来西亚东海岸自驾游-EP1】 跨越2000km游走全马最美沿海公路！从柔佛出发探索沿途各大海滩 关丹超美瀑布 Sungai Pandan Waterfall 海边巨石壁画  彭亨佛教会 品尝美食",
      "tags": [
        "youtube-import"
      ],
      "visit_date": null,
      "video_url": "https://youtu.be/FsqHMUQNiGg",
      "facebook_video_url": null,
      "image_url": null,
      "images": [],
      "status": "active",
      "confidence": 0.35
    },
    {
      "name": "从柔佛一路向北，挑战跨越 2000km 的自驾旅程！",
      "name_cn": null,
      "category": "attraction",
      "region_name": null,
      "country": "Malaysia",
      "address": "从柔佛一路向北，挑战跨越 2000km 的自驾旅程！ Malaysia",
      "latitude": null,
      "longitude": null,
      "description": "From YouTube: 【马来西亚东海岸自驾游-EP1】 跨越2000km游走全马最美沿海公路！从柔佛出发探索沿途各大海滩 关丹超美瀑布 Sungai Pandan Waterfall 海边巨石壁画  彭亨佛教会 品尝美食",
      "tags": [
        "youtube-import"
      ],
      "visit_date": null,
      "video_url": "https://youtu.be/FsqHMUQNiGg",
      "facebook_video_url": null,
      "image_url": null,
      "images": [],
      "status": "active",
      "confidence": 0.35
    },
    {
      "name": "第一站，我们沿着传说中的 3号公路，",
      "name_cn": null,
      "category": "attraction",
      "region_name": null,
      "country": "Malaysia",
      "address": "第一站，我们沿着传说中的 3号公路， Malaysia",
      "latitude": null,
      "longitude": null,
      "description": "From YouTube: 【马来西亚东海岸自驾游-EP1】 跨越2000km游走全马最美沿海公路！从柔佛出发探索沿途各大海滩 关丹超美瀑布 Sungai Pandan Waterfall 海边巨石壁画  彭亨佛教会 品尝美食",
      "tags": [
        "youtube-import"
      ],
      "visit_date": null,
      "video_url": "https://youtu.be/FsqHMUQNiGg",
      "facebook_video_url": null,
      "image_url": null,
      "images": [],
      "status": "active",
      "confidence": 0.35
    },
    {
      "name": "来到了 彭亨关丹 (Kuantan)。 沿途的风景真的太治愈了，左边是椰林，右边是南中国海... 🌴🌊",
      "name_cn": null,
      "category": "attraction",
      "region_name": null,
      "country": "Malaysia",
      "address": "来到了 彭亨关丹 (Kuantan)。 沿途的风景真的太治愈了，左边是椰林，右边是南中国海... 🌴🌊 Malaysia",
      "latitude": null,
      "longitude": null,
      "description": "From YouTube: 【马来西亚东海岸自驾游-EP1】 跨越2000km游走全马最美沿海公路！从柔佛出发探索沿途各大海滩 关丹超美瀑布 Sungai Pandan Waterfall 海边巨石壁画  彭亨佛教会 品尝美食",
      "tags": [
        "youtube-import"
      ],
      "visit_date": null,
      "video_url": "https://youtu.be/FsqHMUQNiGg",
      "facebook_video_url": null,
      "image_url": null,
      "images": [],
      "status": "active",
      "confidence": 0.35
    },
    {
      "name": "这一集带大家去：",
      "name_cn": null,
      "category": "attraction",
      "region_name": null,
      "country": "Malaysia",
      "address": "这一集带大家去： Malaysia",
      "latitude": null,
      "longitude": null,
      "description": "From YouTube: 【马来西亚东海岸自驾游-EP1】 跨越2000km游走全马最美沿海公路！从柔佛出发探索沿途各大海滩 关丹超美瀑布 Sungai Pandan Waterfall 海边巨石壁画  彭亨佛教会 品尝美食",
      "tags": [
        "youtube-import"
      ],
      "visit_date": null,
      "video_url": "https://youtu.be/FsqHMUQNiGg",
      "facebook_video_url": null,
      "image_url": null,
      "images": [],
      "status": "active",
      "confidence": 0.35
    },
    {
      "name": "✅ Sungai Pandan Waterfall: 这个瀑布真的有惊喜！水流巨大，环境超凉爽！💦",
      "name_cn": null,
      "category": "attraction",
      "region_name": null,
      "country": "Malaysia",
      "address": "✅ Sungai Pandan Waterfall: 这个瀑布真的有惊喜！水流巨大，环境超凉爽！💦 Malaysia",
      "latitude": null,
      "longitude": null,
      "description": "From YouTube: 【马来西亚东海岸自驾游-EP1】 跨越2000km游走全马最美沿海公路！从柔佛出发探索沿途各大海滩 关丹超美瀑布 Sungai Pandan Waterfall 海边巨石壁画  彭亨佛教会 品尝美食",
      "tags": [
        "youtube-import"
      ],
      "visit_date": null,
      "video_url": "https://youtu.be/FsqHMUQNiGg",
      "facebook_video_url": null,
      "image_url": null,
      "images": [],
      "status": "active",
      "confidence": 0.35
    },
    {
      "name": "✅ 海边巨石壁画: 没想到岩石上也能画出这么酷的 3D 壁画！🎨",
      "name_cn": null,
      "category": "attraction",
      "region_name": null,
      "country": "Malaysia",
      "address": "✅ 海边巨石壁画: 没想到岩石上也能画出这么酷的 3D 壁画！🎨 Malaysia",
      "latitude": null,
      "longitude": null,
      "description": "From YouTube: 【马来西亚东海岸自驾游-EP1】 跨越2000km游走全马最美沿海公路！从柔佛出发探索沿途各大海滩 关丹超美瀑布 Sungai Pandan Waterfall 海边巨石壁画  彭亨佛教会 品尝美食",
      "tags": [
        "youtube-import"
      ],
      "visit_date": null,
      "video_url": "https://youtu.be/FsqHMUQNiGg",
      "facebook_video_url": null,
      "image_url": null,
      "images": [],
      "status": "active",
      "confidence": 0.35
    },
    {
      "name": "✅ 彭亨佛教会: 湖光倒影，宁静又庄严🙏",
      "name_cn": null,
      "category": "attraction",
      "region_name": null,
      "country": "Malaysia",
      "address": "✅ 彭亨佛教会: 湖光倒影，宁静又庄严🙏 Malaysia",
      "latitude": null,
      "longitude": null,
      "description": "From YouTube: 【马来西亚东海岸自驾游-EP1】 跨越2000km游走全马最美沿海公路！从柔佛出发探索沿途各大海滩 关丹超美瀑布 Sungai Pandan Waterfall 海边巨石壁画  彭亨佛教会 品尝美食",
      "tags": [
        "youtube-import"
      ],
      "visit_date": null,
      "video_url": "https://youtu.be/FsqHMUQNiGg",
      "facebook_video_url": null,
      "image_url": null,
      "images": [],
      "status": "active",
      "confidence": 0.35
    },
    {
      "name": "当然还有一路上的吃吃喝喝！",
      "name_cn": null,
      "category": "attraction",
      "region_name": null,
      "country": "Malaysia",
      "address": "当然还有一路上的吃吃喝喝！ Malaysia",
      "latitude": null,
      "longitude": null,
      "description": "From YouTube: 【马来西亚东海岸自驾游-EP1】 跨越2000km游走全马最美沿海公路！从柔佛出发探索沿途各大海滩 关丹超美瀑布 Sungai Pandan Waterfall 海边巨石壁画  彭亨佛教会 品尝美食",
      "tags": [
        "youtube-import"
      ],
      "visit_date": null,
      "video_url": "https://youtu.be/FsqHMUQNiGg",
      "facebook_video_url": null,
      "image_url": null,
      "images": [],
      "status": "active",
      "confidence": 0.35
    },
    {
      "name": "Imperium Residence预定链接 : https://www.trip.com/t/d8XcgNfUfT2",
      "name_cn": null,
      "category": "attraction",
      "region_name": null,
      "country": "Malaysia",
      "address": "Imperium Residence预定链接 : https://www.trip.com/t/d8XcgNfUfT2 Malaysia",
      "latitude": null,
      "longitude": null,
      "description": "From YouTube: 【马来西亚东海岸自驾游-EP1】 跨越2000km游走全马最美沿海公路！从柔佛出发探索沿途各大海滩 关丹超美瀑布 Sungai Pandan Waterfall 海边巨石壁画  彭亨佛教会 品尝美食",
      "tags": [
        "youtube-import"
      ],
      "visit_date": null,
      "video_url": "https://youtu.be/FsqHMUQNiGg",
      "facebook_video_url": null,
      "image_url": null,
      "images": [],
      "status": "active",
      "confidence": 0.35
    },
    {
      "name": "————————————————————————",
      "name_cn": null,
      "category": "attraction",
      "region_name": null,
      "country": "Malaysia",
      "address": "———————————————————————— Malaysia",
      "latitude": 4.5693754,
      "longitude": 102.2656823,
      "description": "From YouTube: 【马来西亚东海岸自驾游-EP1】 跨越2000km游走全马最美沿海公路！从柔佛出发探索沿途各大海滩 关丹超美瀑布 Sungai Pandan Waterfall 海边巨石壁画  彭亨佛教会 品尝美食",
      "tags": [
        "youtube-import"
      ],
      "visit_date": null,
      "video_url": "https://youtu.be/FsqHMUQNiGg",
      "facebook_video_url": null,
      "image_url": null,
      "images": [],
      "status": "active",
      "confidence": 0.35
    },
    {
      "name": "Chapters",
      "name_cn": null,
      "category": "attraction",
      "region_name": null,
      "country": "Malaysia",
      "address": "Chapters Malaysia",
      "latitude": null,
      "longitude": null,
      "description": "From YouTube: 【马来西亚东海岸自驾游-EP1】 跨越2000km游走全马最美沿海公路！从柔佛出发探索沿途各大海滩 关丹超美瀑布 Sungai Pandan Waterfall 海边巨石壁画  彭亨佛教会 品尝美食",
      "tags": [
        "youtube-import"
      ],
      "visit_date": null,
      "video_url": "https://youtu.be/FsqHMUQNiGg",
      "facebook_video_url": null,
      "image_url": null,
      "images": [],
      "status": "active",
      "confidence": 0.35
    },
    {
      "name": "前往Kuala Rompin",
      "name_cn": null,
      "category": "attraction",
      "region_name": null,
      "country": "Malaysia",
      "address": "前往Kuala Rompin Malaysia",
      "latitude": null,
      "longitude": null,
      "description": "From YouTube: 【马来西亚东海岸自驾游-EP1】 跨越2000km游走全马最美沿海公路！从柔佛出发探索沿途各大海滩 关丹超美瀑布 Sungai Pandan Waterfall 海边巨石壁画  彭亨佛教会 品尝美食",
      "tags": [
        "youtube-import"
      ],
      "visit_date": null,
      "video_url": "https://youtu.be/FsqHMUQNiGg",
      "facebook_video_url": null,
      "image_url": null,
      "images": [],
      "status": "active",
      "confidence": 0.35
    },
    {
      "name": "Pantai Hiburan Rompin",
      "name_cn": null,
      "category": "attraction",
      "region_name": null,
      "country": "Malaysia",
      "address": "Pantai Hiburan Rompin Malaysia",
      "latitude": 2.8065061,
      "longitude": 103.495404,
      "description": "From YouTube: 【马来西亚东海岸自驾游-EP1】 跨越2000km游走全马最美沿海公路！从柔佛出发探索沿途各大海滩 关丹超美瀑布 Sungai Pandan Waterfall 海边巨石壁画  彭亨佛教会 品尝美食",
      "tags": [
        "youtube-import"
      ],
      "visit_date": null,
      "video_url": "https://youtu.be/FsqHMUQNiGg",
      "facebook_video_url": null,
      "image_url": null,
      "images": [],
      "status": "active",
      "confidence": 0.35
    },
    {
      "name": "Pantai Saujana Biru",
      "name_cn": null,
      "category": "attraction",
      "region_name": null,
      "country": "Malaysia",
      "address": "Pantai Saujana Biru Malaysia",
      "latitude": null,
      "longitude": null,
      "description": "From YouTube: 【马来西亚东海岸自驾游-EP1】 跨越2000km游走全马最美沿海公路！从柔佛出发探索沿途各大海滩 关丹超美瀑布 Sungai Pandan Waterfall 海边巨石壁画  彭亨佛教会 品尝美食",
      "tags": [
        "youtube-import"
      ],
      "visit_date": null,
      "video_url": "https://youtu.be/FsqHMUQNiGg",
      "facebook_video_url": null,
      "image_url": null,
      "images": [],
      "status": "active",
      "confidence": 0.35
    },
    {
      "name": "Pekan",
      "name_cn": null,
      "category": "attraction",
      "region_name": null,
      "country": "Malaysia",
      "address": "Pekan Malaysia",
      "latitude": 3.3781961,
      "longitude": 103.2096122,
      "description": "From YouTube: 【马来西亚东海岸自驾游-EP1】 跨越2000km游走全马最美沿海公路！从柔佛出发探索沿途各大海滩 关丹超美瀑布 Sungai Pandan Waterfall 海边巨石壁画  彭亨佛教会 品尝美食",
      "tags": [
        "youtube-import"
      ],
      "visit_date": null,
      "video_url": "https://youtu.be/FsqHMUQNiGg",
      "facebook_video_url": null,
      "image_url": null,
      "images": [],
      "status": "active",
      "confidence": 0.35
    },
    {
      "name": "天乐茶室",
      "name_cn": null,
      "category": "attraction",
      "region_name": null,
      "country": "Malaysia",
      "address": "天乐茶室 Malaysia",
      "latitude": null,
      "longitude": null,
      "description": "From YouTube: 【马来西亚东海岸自驾游-EP1】 跨越2000km游走全马最美沿海公路！从柔佛出发探索沿途各大海滩 关丹超美瀑布 Sungai Pandan Waterfall 海边巨石壁画  彭亨佛教会 品尝美食",
      "tags": [
        "youtube-import"
      ],
      "visit_date": null,
      "video_url": "https://youtu.be/FsqHMUQNiGg",
      "facebook_video_url": null,
      "image_url": null,
      "images": [],
      "status": "active",
      "confidence": 0.35
    },
    {
      "name": "Pantai Lagenda",
      "name_cn": null,
      "category": "attraction",
      "region_name": null,
      "country": "Malaysia",
      "address": "Pantai Lagenda Malaysia",
      "latitude": 5.672525,
      "longitude": 100.5134184,
      "description": "From YouTube: 【马来西亚东海岸自驾游-EP1】 跨越2000km游走全马最美沿海公路！从柔佛出发探索沿途各大海滩 关丹超美瀑布 Sungai Pandan Waterfall 海边巨石壁画  彭亨佛教会 品尝美食",
      "tags": [
        "youtube-import"
      ],
      "visit_date": null,
      "video_url": "https://youtu.be/FsqHMUQNiGg",
      "facebook_video_url": null,
      "image_url": null,
      "images": [],
      "status": "active",
      "confidence": 0.35
    },
    {
      "name": "Jambatan Cherok Paloh",
      "name_cn": null,
      "category": "attraction",
      "region_name": null,
      "country": "Malaysia",
      "address": "Jambatan Cherok Paloh Malaysia",
      "latitude": null,
      "longitude": null,
      "description": "From YouTube: 【马来西亚东海岸自驾游-EP1】 跨越2000km游走全马最美沿海公路！从柔佛出发探索沿途各大海滩 关丹超美瀑布 Sungai Pandan Waterfall 海边巨石壁画  彭亨佛教会 品尝美食",
      "tags": [
        "youtube-import"
      ],
      "visit_date": null,
      "video_url": "https://youtu.be/FsqHMUQNiGg",
      "facebook_video_url": null,
      "image_url": null,
      "images": [],
      "status": "active",
      "confidence": 0.35
    },
    {
      "name": "彭亨佛教会",
      "name_cn": null,
      "category": "attraction",
      "region_name": null,
      "country": "Malaysia",
      "address": "彭亨佛教会 Malaysia",
      "latitude": 3.82376,
      "longitude": 103.3105614,
      "description": "From YouTube: 【马来西亚东海岸自驾游-EP1】 跨越2000km游走全马最美沿海公路！从柔佛出发探索沿途各大海滩 关丹超美瀑布 Sungai Pandan Waterfall 海边巨石壁画  彭亨佛教会 品尝美食",
      "tags": [
        "youtube-import"
      ],
      "visit_date": null,
      "video_url": "https://youtu.be/FsqHMUQNiGg",
      "facebook_video_url": null,
      "image_url": null,
      "images": [],
      "status": "active",
      "confidence": 0.35
    },
    {
      "name": "Imperium Residence",
      "name_cn": null,
      "category": "attraction",
      "region_name": null,
      "country": "Malaysia",
      "address": "Imperium Residence Malaysia",
      "latitude": null,
      "longitude": null,
      "description": "From YouTube: 【马来西亚东海岸自驾游-EP1】 跨越2000km游走全马最美沿海公路！从柔佛出发探索沿途各大海滩 关丹超美瀑布 Sungai Pandan Waterfall 海边巨石壁画  彭亨佛教会 品尝美食",
      "tags": [
        "youtube-import"
      ],
      "visit_date": null,
      "video_url": "https://youtu.be/FsqHMUQNiGg",
      "facebook_video_url": null,
      "image_url": null,
      "images": [],
      "status": "active",
      "confidence": 0.35
    },
    {
      "name": "888美食阁",
      "name_cn": null,
      "category": "attraction",
      "region_name": null,
      "country": "Malaysia",
      "address": "888美食阁 Malaysia",
      "latitude": null,
      "longitude": null,
      "description": "From YouTube: 【马来西亚东海岸自驾游-EP1】 跨越2000km游走全马最美沿海公路！从柔佛出发探索沿途各大海滩 关丹超美瀑布 Sungai Pandan Waterfall 海边巨石壁画  彭亨佛教会 品尝美食",
      "tags": [
        "youtube-import"
      ],
      "visit_date": null,
      "video_url": "https://youtu.be/FsqHMUQNiGg",
      "facebook_video_url": null,
      "image_url": null,
      "images": [],
      "status": "active",
      "confidence": 0.35
    },
    {
      "name": "Kuantan Art Street",
      "name_cn": null,
      "category": "attraction",
      "region_name": null,
      "country": "Malaysia",
      "address": "Kuantan Art Street Malaysia",
      "latitude": 3.8060615,
      "longitude": 103.32811,
      "description": "From YouTube: 【马来西亚东海岸自驾游-EP1】 跨越2000km游走全马最美沿海公路！从柔佛出发探索沿途各大海滩 关丹超美瀑布 Sungai Pandan Waterfall 海边巨石壁画  彭亨佛教会 品尝美食",
      "tags": [
        "youtube-import"
      ],
      "visit_date": null,
      "video_url": "https://youtu.be/FsqHMUQNiGg",
      "facebook_video_url": null,
      "image_url": null,
      "images": [],
      "status": "active",
      "confidence": 0.35
    },
    {
      "name": "Masjid Negeri Pahang",
      "name_cn": null,
      "category": "attraction",
      "region_name": null,
      "country": "Malaysia",
      "address": "Masjid Negeri Pahang Malaysia",
      "latitude": 3.8064539,
      "longitude": 103.3276703,
      "description": "From YouTube: 【马来西亚东海岸自驾游-EP1】 跨越2000km游走全马最美沿海公路！从柔佛出发探索沿途各大海滩 关丹超美瀑布 Sungai Pandan Waterfall 海边巨石壁画  彭亨佛教会 品尝美食",
      "tags": [
        "youtube-import"
      ],
      "visit_date": null,
      "video_url": "https://youtu.be/FsqHMUQNiGg",
      "facebook_video_url": null,
      "image_url": null,
      "images": [],
      "status": "active",
      "confidence": 0.35
    },
    {
      "name": "联兴茶餐室",
      "name_cn": null,
      "category": "attraction",
      "region_name": null,
      "country": "Malaysia",
      "address": "联兴茶餐室 Malaysia",
      "latitude": null,
      "longitude": null,
      "description": "From YouTube: 【马来西亚东海岸自驾游-EP1】 跨越2000km游走全马最美沿海公路！从柔佛出发探索沿途各大海滩 关丹超美瀑布 Sungai Pandan Waterfall 海边巨石壁画  彭亨佛教会 品尝美食",
      "tags": [
        "youtube-import"
      ],
      "visit_date": null,
      "video_url": "https://youtu.be/FsqHMUQNiGg",
      "facebook_video_url": null,
      "image_url": null,
      "images": [],
      "status": "active",
      "confidence": 0.35
    },
    {
      "name": "Sungai Pandan Waterfall",
      "name_cn": null,
      "category": "attraction",
      "region_name": null,
      "country": "Malaysia",
      "address": "Sungai Pandan Waterfall Malaysia",
      "latitude": 3.7895972,
      "longitude": 103.141271,
      "description": "From YouTube: 【马来西亚东海岸自驾游-EP1】 跨越2000km游走全马最美沿海公路！从柔佛出发探索沿途各大海滩 关丹超美瀑布 Sungai Pandan Waterfall 海边巨石壁画  彭亨佛教会 品尝美食",
      "tags": [
        "youtube-import"
      ],
      "visit_date": null,
      "video_url": "https://youtu.be/FsqHMUQNiGg",
      "facebook_video_url": null,
      "image_url": null,
      "images": [],
      "status": "active",
      "confidence": 0.35
    },
    {
      "name": "Mohd Chan",
      "name_cn": null,
      "category": "attraction",
      "region_name": null,
      "country": "Malaysia",
      "address": "Mohd Chan Malaysia",
      "latitude": 3.087331,
      "longitude": 101.5784754,
      "description": "From YouTube: 【马来西亚东海岸自驾游-EP1】 跨越2000km游走全马最美沿海公路！从柔佛出发探索沿途各大海滩 关丹超美瀑布 Sungai Pandan Waterfall 海边巨石壁画  彭亨佛教会 品尝美食",
      "tags": [
        "youtube-import"
      ],
      "visit_date": null,
      "video_url": "https://youtu.be/FsqHMUQNiGg",
      "facebook_video_url": null,
      "image_url": null,
      "images": [],
      "status": "active",
      "confidence": 0.35
    },
    {
      "name": "East Coast Mall",
      "name_cn": null,
      "category": "attraction",
      "region_name": null,
      "country": "Malaysia",
      "address": "East Coast Mall Malaysia",
      "latitude": 3.8181855,
      "longitude": 103.3263277,
      "description": "From YouTube: 【马来西亚东海岸自驾游-EP1】 跨越2000km游走全马最美沿海公路！从柔佛出发探索沿途各大海滩 关丹超美瀑布 Sungai Pandan Waterfall 海边巨石壁画  彭亨佛教会 品尝美食",
      "tags": [
        "youtube-import"
      ],
      "visit_date": null,
      "video_url": "https://youtu.be/FsqHMUQNiGg",
      "facebook_video_url": null,
      "image_url": null,
      "images": [],
      "status": "active",
      "confidence": 0.35
    },
    {
      "name": "Teluk Cempedak",
      "name_cn": null,
      "category": "attraction",
      "region_name": null,
      "country": "Malaysia",
      "address": "Teluk Cempedak Malaysia",
      "latitude": 3.8126555,
      "longitude": 103.3715246,
      "description": "From YouTube: 【马来西亚东海岸自驾游-EP1】 跨越2000km游走全马最美沿海公路！从柔佛出发探索沿途各大海滩 关丹超美瀑布 Sungai Pandan Waterfall 海边巨石壁画  彭亨佛教会 品尝美食",
      "tags": [
        "youtube-import"
      ],
      "visit_date": null,
      "video_url": "https://youtu.be/FsqHMUQNiGg",
      "facebook_video_url": null,
      "image_url": null,
      "images": [],
      "status": "active",
      "confidence": 0.35
    },
    {
      "name": "Loteng",
      "name_cn": null,
      "category": "attraction",
      "region_name": null,
      "country": "Malaysia",
      "address": "Loteng Malaysia",
      "latitude": null,
      "longitude": null,
      "description": "From YouTube: 【马来西亚东海岸自驾游-EP1】 跨越2000km游走全马最美沿海公路！从柔佛出发探索沿途各大海滩 关丹超美瀑布 Sungai Pandan Waterfall 海边巨石壁画  彭亨佛教会 品尝美食",
      "tags": [
        "youtube-import"
      ],
      "visit_date": null,
      "video_url": "https://youtu.be/FsqHMUQNiGg",
      "facebook_video_url": null,
      "image_url": null,
      "images": [],
      "status": "active",
      "confidence": 0.35
    }
  ]
}